aimpyfly/__init__.py
aimpyfly/aim_client.py
aimpyfly/log_utils.py
aimpyfly/oscar_protocol.py
aimpyfly-0.1.1.dist-info/METADATA
aimpyfly-0.1.1.dist-info/WHEEL
aimpyfly-0.1.1.dist-info/top_level.txt
aimpyfly-0.1.1.dist-info/RECORD
