Metadata-Version: 2.1
Name: aimpyfly
Version: 0.1.1
Summary: An AIM client library for python.
Home-page: https://github.com/ukozi/aimpyfly
Author: Lucas J. Chumley
Author-email: Lucas@ukozi.com
Classifier: Programming Language :: Python :: 3
Classifier: License :: OSI Approved :: MIT License
Classifier: Operating System :: OS Independent
Requires-Python: >=3.12
Requires-Dist: asyncio ==3.4.3
Requires-Dist: colorama ==0.4.6
